{"cameraMode":{"drawMode":0,"name":"Shaded","section":"Shading Mode"},"sceneLighting":false,"audioPlay":false,"sceneViewState":{"m_AlwaysRefresh":false,"showFog":true,"showSkybox":false,"showFlares":true,"showImageEffects":true,"showParticleSystems":true,"showVisualEffectGraphs":true,"m_FxEnabled":true},"in2DMode":false,"pivot":{"x":3.0,"y":3.40201473236084,"z":1.1020150184631348},"rotation":{"x":-0.04652664437890053,"y":0.9533902406692505,"z":-0.21701380610466004,"w":-0.20440225303173066},"size":2.7966504096984865,"orthographic":false}